{
  "report_metadata": {
    "title": "Comprehensive CYMBOPOGON SCHOENANTHUS OIL Report",
    "generated_date": "2025-07-14T10:25:47.730304Z",
    "report_type": "ingredient_analysis"
  },
  "ingredient_overview": {
    "inci_name": "CYMBOPOGON SCHOENANTHUS OIL",
    "cas_numbers": [
      "8007-02-1",
      "89998-16-3",
      "89998-14-1"
    ],
    "functions": [
      "Masking",
      "Tonic"
    ],
    "origin": "Vegetal",
    "description": ""
  },
  "safety_information": {
    "safety_score": 2,
    "assessment": "\"Low penalty\" in all categories.",
    "categories": {}
  },
  "product_usage_data": {
    "by_product_type": [
      {
        "product_type": "Classic shampoo",
        "usage_percentage": 0.2,
        "sample_size": 46
      }
    ]
  },
  "reddit_community_analysis": {
    "overview": {
      "total_posts_analyzed": 139,
      "posts_with_comments": 126,
      "comment_coverage_percentage": 90.6
    },
    "sentiment_analysis": {
      "positive_benefits": {
        "total_positive_statements": 4,
        "key_positive_themes": [
          "High Recommendation: 3",
          "Skin Health Improvement: 2",
          "Overall Effectiveness: 1"
        ]
      },
      "negative_cons": {
        "total_negative_statements": 3,
        "key_negative_themes": []
      },
      "overall_sentiment": null,
      "sentiment_keywords": {
        "positive": {
          "count": 0,
          "percentage": 0.0
        },
        "negative": {
          "count": 0,
          "percentage": 0.0
        }
      },
      "sentiment_posts": {
        "positive_sentiment_posts": 53,
        "negative_sentiment_posts": 17
      }
    },
    "dosage_effectiveness": {
      "total_dosage_statements": 9,
      "effective_dosage_mentions": 0,
      "most_common_dosages": []
    },
    "category_breakdown": [
      {
        "category": "Ingredient Usage Patterns",
        "post_count": 67,
        "percentage": 48.2
      },
      {
        "category": "Treatment Experiences",
        "post_count": 103,
        "percentage": 74.1
      },
      {
        "category": "Product Recommendations",
        "post_count": 111,
        "percentage": 79.9
      },
      {
        "category": "Progress Report",
        "post_count": 70,
        "percentage": 50.4
      },
      {
        "category": "Side Effects",
        "post_count": 42,
        "percentage": 30.2
      },
      {
        "category": "Combination Therapy",
        "post_count": 136,
        "percentage": 97.8
      },
      {
        "category": "Humor Meme",
        "post_count": 35,
        "percentage": 25.2
      },
      {
        "category": "Seeking Advice",
        "post_count": 128,
        "percentage": 92.1
      },
      {
        "category": "Scientific Discussion",
        "post_count": 29,
        "percentage": 20.9
      },
      {
        "category": "Dosage Questions",
        "post_count": 29,
        "percentage": 20.9
      }
    ],
    "ingredient_combinations": {
      "top_combinations": [],
      "ingredients_mentioned_in_comments": []
    },
    "product_forms": [],
    "body_parts_usage": [],
    "temporal_patterns": {
      "posts_by_year": []
    },
    "subreddit_distribution": [],
    "key_insights": [],
    "brands_mentioned": []
  }
}