{
  "ingredient_overview": {
    "inci_name": "POLYSORBATE 20",
    "cas_numbers": [
      "9005-64-5"
    ],
    "functions": [
      "Emulsifying",
      "Surfactant"
    ],
    "origin": "Vegetal, Synthetic",
    "description": "Polysorbate 20 or Tween 20 is a nonionic surfactant and a sorbitol-derived emulsifier based on fruits and berries. It helps to dilute essential oils or perfume in water-based cosmetics like lotions, creams, gels."
  },
  "safety_information": {
    "safety_score": 5,
    "assessment": "\"Medium penalty\" in all categories.",
    "categories": {}
  },
  "product_usage_data": {
    "by_product_type": [
      {
        "product_type": "Classic shampoo",
        "usage_percentage": 4.4,
        "sample_size": 1026
      },
      {
        "product_type": "Shower gel",
        "usage_percentage": 5.15,
        "sample_size": 921
      },
      {
        "product_type": "Face Lotion and Toner",
        "usage_percentage": 11.8,
        "sample_size": 601
      },
      {
        "product_type": "Hair conditioner",
        "usage_percentage": 5.0,
        "sample_size": 550
      },
      {
        "product_type": "Specific hair care",
        "usage_percentage": 8.41,
        "sample_size": 531
      }
    ]
  },
  "reddit_community_analysis": {
    "overview": {
      "total_posts_analyzed": 139,
      "posts_with_comments": 139,
      "comment_coverage_percentage": 100.0
    },
    "sentiment_analysis": {
      "sentiment_keywords": {
        "positive": {
          "count": 311,
          "percentage": 63.0
        },
        "negative": {
          "count": 183,
          "percentage": 37.0
        }
      },
      "overall_sentiment": "POSITIVE",
      "sentiment_posts": {
        "positive_sentiment_posts": 82,
        "negative_sentiment_posts": 21
      }
    },
    "category_breakdown": [],
    "ingredient_combinations": {
      "top_combinations": [],
      "ingredients_mentioned_in_comments": []
    },
    "product_forms": [],
    "body_parts_usage": [],
    "temporal_patterns": {
      "posts_by_year": []
    },
    "subreddit_distribution": [],
    "key_insights": [],
    "brands_mentioned": []
  }
}