{
  "report_metadata": {
    "title": "Comprehensive RICINUS COMMUNIS SEED OIL Report",
    "generated_date": "2025-07-14T10:25:47.698944Z",
    "report_type": "ingredient_analysis"
  },
  "ingredient_overview": {
    "inci_name": "RICINUS COMMUNIS SEED OIL",
    "cas_numbers": [
      "8001-79-4"
    ],
    "functions": [
      "Masking",
      "Skin conditioning",
      "Perfuming"
    ],
    "origin": "Vegetal",
    "description": "Castor oil is a vegetable oil extracted from seeds, it is mainly made up of fatty acids (mostly ricinoleic acid). This oil is used because of its numerous properties in cosmetics: it promotes the uniform distribution of pigments in a cosmetic product, it penetrates the stratum corneum and acts in depth, it moisturizes and protects. In hair care, it has toning properties and protects the hair (film-forming agent). It is also very used in lip care, it makes them soft and gives them shine. In makeup, it is used to promote a good distribution of colors. It is allowed in organic."
  },
  "safety_information": {
    "safety_score": 0,
    "assessment": "\"No penalty\" in all categories.",
    "categories": {}
  },
  "product_usage_data": {
    "by_product_type": [
      {
        "product_type": "Lipstick",
        "usage_percentage": 25.38,
        "sample_size": 2994
      },
      {
        "product_type": "Lip balm",
        "usage_percentage": 55.25,
        "sample_size": 2217
      },
      {
        "product_type": "Gloss and lip gloss",
        "usage_percentage": 23.14,
        "sample_size": 719
      },
      {
        "product_type": "Mascara",
        "usage_percentage": 19.67,
        "sample_size": 628
      },
      {
        "product_type": "Classic shampoo",
        "usage_percentage": 2.53,
        "sample_size": 590
      }
    ]
  },
  "reddit_community_analysis": {
    "overview": {
      "total_posts_analyzed": 87,
      "posts_with_comments": 68,
      "comment_coverage_percentage": 78.2
    },
    "sentiment_analysis": {
      "positive_benefits": {
        "total_positive_statements": 0,
        "key_positive_themes": []
      },
      "negative_cons": {
        "total_negative_statements": 0,
        "key_negative_themes": []
      },
      "overall_sentiment": null,
      "sentiment_keywords": {
        "positive": {
          "count": 0,
          "percentage": 0.0
        },
        "negative": {
          "count": 0,
          "percentage": 0.0
        }
      },
      "sentiment_posts": {
        "positive_sentiment_posts": 26,
        "negative_sentiment_posts": 9
      }
    },
    "dosage_effectiveness": {
      "total_dosage_statements": 2,
      "effective_dosage_mentions": 0,
      "most_common_dosages": []
    },
    "category_breakdown": [
      {
        "category": "Ingredient Usage Patterns",
        "post_count": 53,
        "percentage": 60.9
      },
      {
        "category": "Treatment Experiences",
        "post_count": 53,
        "percentage": 60.9
      },
      {
        "category": "Product Recommendations",
        "post_count": 75,
        "percentage": 86.2
      },
      {
        "category": "Progress Report",
        "post_count": 29,
        "percentage": 33.3
      },
      {
        "category": "Side Effects",
        "post_count": 32,
        "percentage": 36.8
      },
      {
        "category": "Dosage Questions",
        "post_count": 26,
        "percentage": 29.9
      },
      {
        "category": "Combination Therapy",
        "post_count": 84,
        "percentage": 96.6
      },
      {
        "category": "Humor Meme",
        "post_count": 20,
        "percentage": 23.0
      },
      {
        "category": "Seeking Advice",
        "post_count": 77,
        "percentage": 88.5
      },
      {
        "category": "Scientific Discussion",
        "post_count": 16,
        "percentage": 18.4
      }
    ],
    "ingredient_combinations": {
      "top_combinations": [],
      "ingredients_mentioned_in_comments": []
    },
    "product_forms": [],
    "body_parts_usage": [],
    "temporal_patterns": {
      "posts_by_year": []
    },
    "subreddit_distribution": [],
    "key_insights": [],
    "brands_mentioned": []
  }
}