{
  "dashboard_info": {
    "title": "Reddit Engagement Dashboard",
    "subtitle": "Skincare & Haircare Communities",
    "last_updated": "2026-02-23T04:47:32.023852+00:00",
    "total_posts": 21,
    "subreddits_count": 6,
    "refresh_interval": "2 hours",
    "run_id": "2026-02-23_04_47",
    "run_date": "2026-02-23",
    "run_time": "04_47"
  },
  "posts": [
    {
      "id": "1qqz45o",
      "title": "To Blowdry or Airdry?",
      "content": "I have heard that blowdrying your hair can cause heat damage, and that products to prevent heat damage can cause build-up on the hair that can weigh it down and make it seem limp and heavy. I've ALSO heard that air-drying your hair, especially if it takes an hour+ to dry, can lead to  unhealthy scalp via fungus/bacteria/yeast. This claim doesn't make sense to me because, where did those things come from on a healthy scalp? Hair scientists, what is the actual deal about how we should dry our hair?",
      "content_preview": "I have heard that blowdrying your hair can cause heat damage, and that products to prevent heat damage can cause build-up on the hair that can weigh i...",
      "content_length": 501,
      "subreddit": "HaircareScience",
      "subreddit_color": "#00c851",
      "subreddit_display": "r/HaircareScience",
      "url": "https://reddit.com/r/HaircareScience/comments/1qqz45o/to_blowdry_or_airdry/",
      "score": 124,
      "comments": 12,
      "engagement_score": 136,
      "created_utc": 1769758945.0,
      "age_human": "23d ago",
      "age_seconds": 2063107.0238559246,
      "author": "QueerestBean",
      "has_images": false,
      "image_urls": [],
      "image_count": 0,
      "flair": "Question",
      "is_self": true,
      "permalink": "/r/HaircareScience/comments/1qqz45o/to_blowdry_or_airdry/",
      "relevance_score": 100,
      "combined_score": 28.1,
      "engagement_score_original": 136,
      "opportunity_rating": "medium",
      "context": {
        "triggered_keywords": [
          "scalp",
          "products"
        ],
        "help_type": "hair_concern",
        "help_type_confidence": 0.2,
        "expertise_match": [
          "product recommendations",
          "vitamin c serum",
          "hair loss treatment",
          "scalp health",
          "curly hair care",
          "hair growth",
          "hair oils",
          "haircare",
          "product"
        ],
        "response_angles": [
          "Share your hair care experience",
          "Suggest products for their hair type",
          "Recommend professional consultation if needed"
        ],
        "urgency_level": "medium",
        "competition_analysis": {
          "comment_count": 12,
          "engagement_level": "high",
          "response_opportunity": "moderate"
        },
        "confidence_score": 1.0,
        "response_suggestions": [
          "General match - provide helpful information and ask questions to understand their needs better",
          "Your expertise in product recommendations, vitamin c serum is highly relevant",
          "Consider these approaches: Share your hair care experience, Suggest products for their hair type"
        ]
      }
    },
    {
      "id": "1rc612u",
      "title": "Brown or Blonde?!",
      "content": "I grew up with blonde hair, but as I got older it got darker. When I was a teenager I started getting highlights. I didn’t change it up until a few months ago when I decided to go closer to my natural color. My hair stylist decided to just tone it so it would be temporary in case I didn’t like it. That’s why you can still see some highlights. I like the brown, but I feel like I don’t stand out as much and I look plain. In your opinion, which hair color suits me best? I’m planning to go back to my hair dresser soon but I haven’t decided if I want to go back to highlights or dye my hair brown permanently. The first 3 pics are me with brown hair, the last 3 are me with blonder hair. ",
      "content_preview": "I grew up with blonde hair, but as I got older it got darker. When I was a teenager I started getting highlights. I didn’t change it up until a few mo...",
      "content_length": 689,
      "subreddit": "Hair",
      "subreddit_color": "#e74c3c",
      "subreddit_display": "r/Hair",
      "url": "https://reddit.com/r/Hair/comments/1rc612u/brown_or_blonde/",
      "score": 9,
      "comments": 13,
      "engagement_score": 22,
      "created_utc": 1771815806.0,
      "age_human": "1h ago",
      "age_seconds": 6246.025072097778,
      "author": "Sierralovescats",
      "has_images": true,
      "image_urls": [
        {
          "url": "https://preview.redd.it/9kfdklz0u5lg1.jpg?width=2316&format=pjpg&auto=webp&s=d28594579ddf5aebc35f81e65fa35be7737c152f",
          "width": 2316,
          "height": 3088,
          "type": "gallery"
        },
        {
          "url": "https://preview.redd.it/no4kuyy0u5lg1.jpg?width=2316&format=pjpg&auto=webp&s=38c3a54dda20b740f96f854cbb0912bf3daaca39",
          "width": 2316,
          "height": 3088,
          "type": "gallery"
        },
        {
          "url": "https://preview.redd.it/iimjezy0u5lg1.jpg?width=2316&format=pjpg&auto=webp&s=2ddf6d59df835d54d2b44b6af9081aa8dee0b023",
          "width": 2316,
          "height": 3088,
          "type": "gallery"
        },
        {
          "url": "https://preview.redd.it/alyroyy0u5lg1.jpg?width=2316&format=pjpg&auto=webp&s=603fc5b575a9014f3096f3aa5ec650fa645ffb3b",
          "width": 2316,
          "height": 3088,
          "type": "gallery"
        },
        {
          "url": "https://preview.redd.it/er74xuy0u5lg1.jpg?width=2316&format=pjpg&auto=webp&s=13fa17fe7626ef5d0665fea22a1f25d6ff612106",
          "width": 2316,
          "height": 3088,
          "type": "gallery"
        },
        {
          "url": "https://preview.redd.it/s0tcqaz0u5lg1.jpg?width=2316&format=pjpg&auto=webp&s=ae68a93e279fb070d05d03c27b81930612a79dca",
          "width": 2316,
          "height": 3088,
          "type": "gallery"
        }
      ],
      "image_count": 6,
      "flair": "Help",
      "is_self": false,
      "permalink": "/r/Hair/comments/1rc612u/brown_or_blonde/",
      "relevance_score": 100,
      "combined_score": 14.286704292610288,
      "engagement_score_original": 22,
      "opportunity_rating": "low",
      "context": {
        "triggered_keywords": [],
        "help_type": "product_recommendation",
        "help_type_confidence": 0.2,
        "expertise_match": [
          "vitamin c serum",
          "hair loss treatment",
          "curly hair care",
          "hair growth",
          "hair oils",
          "haircare"
        ],
        "response_angles": [
          "Recommend specific products you've used",
          "Suggest budget-friendly alternatives",
          "Share your experience with similar products"
        ],
        "urgency_level": "medium",
        "competition_analysis": {
          "comment_count": 13,
          "engagement_level": "high",
          "response_opportunity": "moderate"
        },
        "confidence_score": 1.0,
        "response_suggestions": [
          "General match - provide helpful information and ask questions to understand their needs better",
          "Your expertise in vitamin c serum, hair loss treatment is highly relevant",
          "Consider these approaches: Recommend specific products you've used, Suggest budget-friendly alternatives"
        ]
      }
    },
    {
      "id": "1rc5jf1",
      "title": "Any advice will help and why is the top straight??",
      "content": "",
      "content_preview": "",
      "content_length": 0,
      "subreddit": "curlyhair",
      "subreddit_color": "#ff6b35",
      "subreddit_display": "r/curlyhair",
      "url": "https://reddit.com/r/curlyhair/comments/1rc5jf1/any_advice_will_help_and_why_is_the_top_straight/",
      "score": 2,
      "comments": 14,
      "engagement_score": 16,
      "created_utc": 1771814437.0,
      "age_human": "2h ago",
      "age_seconds": 7615.02560710907,
      "author": "Same-Entrepreneur373",
      "has_images": true,
      "image_urls": [
        {
          "url": "https://preview.redd.it/8whlb5xzp5lg1.jpg?width=1242&format=pjpg&auto=webp&s=de4be345fb69296839e456f88655aca42f64627c",
          "width": 1242,
          "height": 2208,
          "type": "gallery"
        },
        {
          "url": "https://preview.redd.it/sfmk70xzp5lg1.jpg?width=1242&format=pjpg&auto=webp&s=b8d6f8f9f0eed7dfe4db15c90a98505077422f0e",
          "width": 1242,
          "height": 2208,
          "type": "gallery"
        }
      ],
      "image_count": 2,
      "flair": "Help!",
      "is_self": false,
      "permalink": "/r/curlyhair/comments/1rc5jf1/any_advice_will_help_and_why_is_the_top_straight/",
      "relevance_score": 100,
      "combined_score": 13.495575389642408,
      "engagement_score_original": 16,
      "opportunity_rating": "low",
      "context": {
        "triggered_keywords": [],
        "help_type": "troubleshooting",
        "help_type_confidence": 0.1,
        "expertise_match": [
          "vitamin c serum",
          "problem-solving"
        ],
        "response_angles": [
          "Share how you solved a similar problem",
          "Suggest diagnostic questions to ask",
          "Recommend gentle solutions to try first"
        ],
        "urgency_level": "low",
        "competition_analysis": {
          "comment_count": 14,
          "engagement_level": "high",
          "response_opportunity": "moderate"
        },
        "confidence_score": 0.43000000000000005,
        "response_suggestions": [
          "General match - provide helpful information and ask questions to understand their needs better",
          "Your expertise in vitamin c serum, problem-solving is highly relevant",
          "Consider these approaches: Share how you solved a similar problem, Suggest diagnostic questions to ask"
        ]
      }
    },
    {
      "id": "1rc5jsi",
      "title": "Top part of my hair refuses to curl guy",
      "content": "Routine:\n\nShampoo: Head n shoulders  \n\nConditioner: None \n\nLeave in: Skala \n\nGel: Ouidad (white one) \n\nWas diffused in this picture but not fully \n\nMy hair refuses to curl on top. I think it’s just how my 2c-3a hair type presents. My hair gets curlier the longer it is. I think my hair needs a longer strand of hair to form a curl. I use a denman brush to brush my curls. Sometimes I blow dry my hair with a diffuser but more often than not I let it air dry. \n\nI have never gotten a curly hair cut due to it being so expensive. But thinking of getting one. I am thinking I can get more layers at the top and some side bangs for a rounder shape. Any ideas!",
      "content_preview": "Routine:\n\nShampoo: Head n shoulders  \n\nConditioner: None \n\nLeave in: Skala \n\nGel: Ouidad (white one) \n\nWas diffused in this picture but not fully \n\nMy...",
      "content_length": 655,
      "subreddit": "curlyhair",
      "subreddit_color": "#ff6b35",
      "subreddit_display": "r/curlyhair",
      "url": "https://reddit.com/r/curlyhair/comments/1rc5jsi/top_part_of_my_hair_refuses_to_curl_guy/",
      "score": 10,
      "comments": 17,
      "engagement_score": 27,
      "created_utc": 1771814465.0,
      "age_human": "2h ago",
      "age_seconds": 7587.025837898254,
      "author": "Floofy5267",
      "has_images": true,
      "image_urls": [
        {
          "url": "https://preview.redd.it/xeqwrny2q5lg1.jpeg?auto=webp&s=2b4858abe6d673dffc7758bc3d3dda31a2d5f8c7",
          "width": 2316,
          "height": 3088,
          "type": "preview"
        }
      ],
      "image_count": 1,
      "flair": "Help!",
      "is_self": false,
      "permalink": "/r/curlyhair/comments/1rc5jsi/top_part_of_my_hair_refuses_to_curl_guy/",
      "relevance_score": 100,
      "combined_score": 13.23012151041627,
      "engagement_score_original": 27,
      "opportunity_rating": "low",
      "context": {
        "triggered_keywords": [
          "curly hair",
          "shampoo",
          "routine",
          "conditioner"
        ],
        "help_type": "hair_concern",
        "help_type_confidence": 0.2,
        "expertise_match": [
          "skincare routine",
          "vitamin c serum",
          "hair loss treatment",
          "curly hair care",
          "hair growth",
          "hair oils",
          "skincare",
          "haircare"
        ],
        "response_angles": [
          "Share your hair care experience",
          "Suggest products for their hair type",
          "Recommend professional consultation if needed"
        ],
        "urgency_level": "low",
        "competition_analysis": {
          "comment_count": 17,
          "engagement_level": "high",
          "response_opportunity": "limited"
        },
        "confidence_score": 1.0,
        "response_suggestions": [
          "General match - provide helpful information and ask questions to understand their needs better",
          "Your expertise in skincare routine, vitamin c serum is highly relevant",
          "Consider these approaches: Share your hair care experience, Suggest products for their hair type"
        ]
      }
    },
    {
      "id": "1rc6g79",
      "title": "Routine suggestions",
      "content": "Hello!\n\nI would like help with my hair routine. As of right now, I shampoo and condition every morning with Ouidad’s Curl Shaper double duty conditioner and good as new shampoo, then I apply their Climate control stronger hold gel, comb it through my hair with a wide tooth comb, rough it up however I like, and diffuse it. I have no protection for my hair while I am sleeping. This routine is good, but it costs a lot of money and takes a long time. Does anyone have suggestions for a better routine, perhaps with the same products? I know most people don’t wash their hair every day, but I don’t know how to go about doing that. Any advice is appreciated, thank you!",
      "content_preview": "Hello!\n\nI would like help with my hair routine. As of right now, I shampoo and condition every morning with Ouidad’s Curl Shaper double duty condition...",
      "content_length": 668,
      "subreddit": "curlyhair",
      "subreddit_color": "#ff6b35",
      "subreddit_display": "r/curlyhair",
      "url": "https://reddit.com/r/curlyhair/comments/1rc6g79/routine_suggestions/",
      "score": 2,
      "comments": 1,
      "engagement_score": 3,
      "created_utc": 1771817016.0,
      "age_human": "1h ago",
      "age_seconds": 5036.02628993988,
      "author": "Sad_Club8574",
      "has_images": true,
      "image_urls": [
        {
          "url": "https://preview.redd.it/1923ar2ox5lg1.jpeg?auto=webp&s=722a8f30733ee0e6d59d268107a83bd0c4b3029c",
          "width": 1802,
          "height": 1834,
          "type": "preview"
        }
      ],
      "image_count": 1,
      "flair": "Help!",
      "is_self": false,
      "permalink": "/r/curlyhair/comments/1rc6g79/routine_suggestions/",
      "relevance_score": 100,
      "combined_score": 12.430608188619216,
      "engagement_score_original": 3,
      "opportunity_rating": "low",
      "context": {
        "triggered_keywords": [
          "shampoo",
          "routine",
          "conditioner",
          "products"
        ],
        "help_type": "routine_help",
        "help_type_confidence": 0.4,
        "expertise_match": [
          "skincare routine",
          "product recommendations",
          "vitamin c serum",
          "hair loss treatment",
          "curly hair care",
          "hair growth",
          "hair oils",
          "skincare",
          "haircare",
          "product",
          "problem-solving"
        ],
        "response_angles": [
          "Share your personal routine experience",
          "Suggest a step-by-step routine based on their skin type",
          "Recommend products for each step"
        ],
        "urgency_level": "low",
        "competition_analysis": {
          "comment_count": 1,
          "engagement_level": "low",
          "response_opportunity": "good"
        },
        "confidence_score": 1.0,
        "response_suggestions": [
          "General match - provide helpful information and ask questions to understand their needs better",
          "Your expertise in skincare routine, product recommendations is highly relevant",
          "Consider these approaches: Share your personal routine experience, Suggest a step-by-step routine based on their skin type"
        ]
      }
    },
    {
      "id": "1rbxcit",
      "title": "Skincare habits that TRANSFORMED my skin",
      "content": "I started experimenting with skincare inspite of having absolutely clear skin to begin with due to it being trendy.\n\nAbsolutely WRECKED my skin barrier.\n\nYet, I continued and nothing seemed to work. Then i started watching dr.shireen idriss’s videos and started implementing her tips and my skin did a 180 in less than 8 months!\n\nHere’s everything that worked for me\n\n\\- warming up my cleanser for 30 secs and then cleansing for atleast 1 minute. I use the minimalist oat cleanser\n\n\\- ⁠ADAPALENE IS MY SAVING GRACE. I didn’t wanna try a strong retinoid and acne was my major concern so I started with adapalene and it saved my skin 😭 I do an adapalene ointment 3 days a week sunday, monday and Thursday \n\n\\- ⁠Using azelaic acid serum by anua everyday especially pairing it with adapalene made a lot of difference for me\n\n\\- ⁠Hypochlorous acid spray after gym or whenever i sweat and also after i ’ve done my nightly skincare routine is just \\*chef’s kiss\\* I use woundfix or oxum spray\n\n\\- ⁠i use minimalists aha bha and pha peel twice a month just for rejuvenating the skin whenever need b but i make it a point to not do it in my retinoid nights because my skin isn’t that tough yet\n\n\\- ⁠every saturday I dnt use any skincare just cleanse, moisturiser for which i use the bioderma atoderm and a diaper rash cream to allow my skin to take a breather \n\nAnd apart from these ofcourse sunscreen in the morning, i dont use cleanser in the morning and also a vitamin c serum currently experimenting with the pilgrim one previously was using minimalist’s 10%\n\nThese habits helped me get my clear skin back and eventhough I have some occasional breakouts they’re not that bad 😭\n\nA lot of trial and error and research later i just wanted to share it because these tips are rather generic and something anyone can try out in their skincare journey",
      "content_preview": "I started experimenting with skincare inspite of having absolutely clear skin to begin with due to it being trendy.\n\nAbsolutely WRECKED my skin barrie...",
      "content_length": 1839,
      "subreddit": "IndianSkincareAddicts",
      "subreddit_color": "#ff4500",
      "subreddit_display": "r/IndianSkincareAddicts",
      "url": "https://reddit.com/r/IndianSkincareAddicts/comments/1rbxcit/skincare_habits_that_transformed_my_skin/",
      "score": 18,
      "comments": 12,
      "engagement_score": 30,
      "created_utc": 1771793671.0,
      "age_human": "7h ago",
      "age_seconds": 28381.026731967926,
      "author": "Ok-Peak6107",
      "has_images": true,
      "image_urls": [
        {
          "url": "https://preview.redd.it/hrjgnmv804lg1.jpg?width=1170&format=pjpg&auto=webp&s=0598878a07381d03b61de983df4f9679471e8e03",
          "width": 1170,
          "height": 2532,
          "type": "gallery"
        },
        {
          "url": "https://preview.redd.it/u906yzv804lg1.jpg?width=3840&format=pjpg&auto=webp&s=5e5a5633c98ae89d6ff8a366414e94008b49e706",
          "width": 3840,
          "height": 3840,
          "type": "gallery"
        }
      ],
      "image_count": 2,
      "flair": "I Followed Posting Rules",
      "is_self": false,
      "permalink": "/r/IndianSkincareAddicts/comments/1rbxcit/skincare_habits_that_transformed_my_skin/",
      "relevance_score": 100,
      "combined_score": 11.281469215505654,
      "engagement_score_original": 30,
      "opportunity_rating": "low",
      "context": {
        "triggered_keywords": [
          "cleansing",
          "vitamin c",
          "routine",
          "acne",
          "pha",
          "bha",
          "skincare routine",
          "vitamin c serum",
          "azelaic acid",
          "skincare",
          "sunscreen",
          "aha"
        ],
        "help_type": "routine_help",
        "help_type_confidence": 0.3,
        "expertise_match": [
          "skincare routine",
          "acne treatment",
          "sensitive skin",
          "vitamin c serum",
          "skin barrier repair",
          "pH balance",
          "salicylic acid",
          "hyaluronic acid",
          "sunscreen",
          "cleansing",
          "curly hair care",
          "skincare",
          "ingredients",
          "scientific",
          "problem-solving"
        ],
        "response_angles": [
          "Share your personal routine experience",
          "Suggest a step-by-step routine based on their skin type",
          "Recommend products for each step"
        ],
        "urgency_level": "medium",
        "competition_analysis": {
          "comment_count": 12,
          "engagement_level": "high",
          "response_opportunity": "moderate"
        },
        "confidence_score": 1.0,
        "response_suggestions": [
          "General match - provide helpful information and ask questions to understand their needs better",
          "Your expertise in skincare routine, acne treatment is highly relevant",
          "Consider these approaches: Share your personal routine experience, Suggest a step-by-step routine based on their skin type"
        ]
      }
    },
    {
      "id": "1r21dyc",
      "title": "Confused about hyaluronic acid",
      "content": "Generally we are taught that (apart from needing a normal amount of hydration present in skin and hair, aka when it can become a problem in dry climates) that under normal conditions, wet hair aka water content in the hair means weaker hair while it is wet. I do understand that is exaggerated in some cases, but the core of the principle itself is true, as far as I understand.\n\nI’m seeing hyaluronic acid in some leave in products. I understand that it’s water soluble and in shampoo and conditioner it’s washed out, so the implication of it being in wash out products isn’t very consequential. \n\nI’m confused about the implications of it being in leave in products. If the hyaluronic acid does draw water content into the hair, is that such that the hair is in a weaker state when that happens? Or is that not the case or something else is happening? I guess I’m trying to understand, is it just more harmless marketing that is just throwing in an ingredient that isn’t necessarily going to cause a problem, or could it make the hair weaker temporarily due to the increase in water",
      "content_preview": "Generally we are taught that (apart from needing a normal amount of hydration present in skin and hair, aka when it can become a problem in dry climat...",
      "content_length": 1084,
      "subreddit": "HaircareScience",
      "subreddit_color": "#00c851",
      "subreddit_display": "r/HaircareScience",
      "url": "https://reddit.com/r/HaircareScience/comments/1r21dyc/confused_about_hyaluronic_acid/",
      "score": 46,
      "comments": 2,
      "engagement_score": 48,
      "created_utc": 1770826001.0,
      "age_human": "11d ago",
      "age_seconds": 996051.0275430679,
      "author": "pemberley22",
      "has_images": false,
      "image_urls": [],
      "image_count": 0,
      "flair": "Question",
      "is_self": true,
      "permalink": "/r/HaircareScience/comments/1r21dyc/confused_about_hyaluronic_acid/",
      "relevance_score": 100,
      "combined_score": 10.500000000000002,
      "engagement_score_original": 48,
      "opportunity_rating": "low",
      "context": {
        "triggered_keywords": [
          "shampoo",
          "hyaluronic acid",
          "conditioner",
          "products",
          "hydration"
        ],
        "help_type": "skin_concern",
        "help_type_confidence": 0.3,
        "expertise_match": [
          "product recommendations",
          "sensitive skin",
          "vitamin c serum",
          "skin barrier repair",
          "ingredient interactions",
          "salicylic acid",
          "hyaluronic acid",
          "hair loss treatment",
          "curly hair care",
          "hair growth",
          "hair oils",
          "haircare",
          "ingredients",
          "product",
          "problem-solving"
        ],
        "response_angles": [
          "Share your experience with similar skin concerns",
          "Suggest gentle, proven solutions",
          "Recommend a consultation approach"
        ],
        "urgency_level": "low",
        "competition_analysis": {
          "comment_count": 2,
          "engagement_level": "low",
          "response_opportunity": "good"
        },
        "confidence_score": 1.0,
        "response_suggestions": [
          "General match - provide helpful information and ask questions to understand their needs better",
          "Your expertise in product recommendations, sensitive skin is highly relevant",
          "Consider these approaches: Share your experience with similar skin concerns, Suggest gentle, proven solutions"
        ]
      }
    },
    {
      "id": "1rc0y77",
      "title": "Affordable Diffuser Recs + a few Q’s",
      "content": "This ended up longer than planned but if you read it all XOXO you’re a doll!\n\nHiya! I recently broke my diffuser attachment for my blowdryer (Nano titanium by BaBylissPro, 2.5in I think) which was bought on Amazon and not the same brand as my blowdryer. I’m looking into getting a quality/better one but not super expensive. I’m a college student so money is a bit tight but i cant just keep replacing it either. The one i had you twisted and attached to the end of the blowdryer, it would come off pretty easily which causes issues and it looked like the plastic inside was starting to melt and burn. I was able to save it from breaking a few times but not this one.\n\nI also have very thick hair and it is about tailbone length if that changes anything for recommendations. I am new to diffusing, maybe 3 months into learning. I was never taught how to manage my hair and how to care/style it so i’m learning as I go. I used to just flat iron it but i am finally embracing my hair, especially my curls!\n\nI am unsure of the big differences between a finger diffuser and a hand one or bowel. Are the ones with a hood that you attach any good? The only one i can find specifically for my blowdryer brand is a “finger diffuser”. Is there a post here that maybe goes over those? Or could someone help me figure out whats best for me? I tend to hover(?) my roots and then i think its called pixie(?) or fairie(?) diffusing when i have the diffuser facing up and my hair on it. (These are new terms for me, sorry if incorrect, love a link to info) Hair typing for curl pattern has always confused me, especially with how finicky and day to day/length to length my hair can be. I don’t know my porosity, i know i should figure these things out as they are used so much in these spaces.\n\nAll recommendations welcome, i can put the more expensive ones away in a list for later, but affordable and lasting is best.  A bit of durability is also great, i’m very clutzy with poor grip.\n\nAny other advice, info, products, etc you recommend or I should know or wish you knew starting out is also welcome\n\nMy routine:\n\nAs I am pom shampoo, occasionally the conditioner, Skala deep conditioner (yellow, currently trying this brand got a cheap bundle. Like the yellow and blue so far, yellow smells sooo good), Mielle leave in pom prayer hands, Microfiber towel plop \\~10min, Mouse def mouse scrunched, Got2be gel mixed with water in my hands then prayer hands and scrunched (first gel to actually give me a cast, but other gels may have if i was diffusing at the time.), luesta biotin and collagen heat protectant spray (new and love it, smells good too), Diffuse roots then diffuse in sections, still learning how to refresh (tips welcome) so its not an everyday thing, i sleep in a bonnet or silk scarf with a mulberry silk pillowcase\n\nEdit:: I’ll look more in the wiki when i have some down time, i’m back to studying for exams!",
      "content_preview": "This ended up longer than planned but if you read it all XOXO you’re a doll!\n\nHiya! I recently broke my diffuser attachment for my blowdryer (Nano tit...",
      "content_length": 2914,
      "subreddit": "curlyhair",
      "subreddit_color": "#ff6b35",
      "subreddit_display": "r/curlyhair",
      "url": "https://reddit.com/r/curlyhair/comments/1rc0y77/affordable_diffuser_recs_a_few_qs/",
      "score": 2,
      "comments": 2,
      "engagement_score": 4,
      "created_utc": 1771802231.0,
      "age_human": "5h ago",
      "age_seconds": 19821.028137922287,
      "author": "szikkia",
      "has_images": false,
      "image_urls": [],
      "image_count": 0,
      "flair": "Help!",
      "is_self": true,
      "permalink": "/r/curlyhair/comments/1rc0y77/affordable_diffuser_recs_a_few_qs/",
      "relevance_score": 100,
      "combined_score": 10.480024661119337,
      "engagement_score_original": 4,
      "opportunity_rating": "low",
      "context": {
        "triggered_keywords": [
          "shampoo",
          "routine",
          "conditioner",
          "products"
        ],
        "help_type": "product_recommendation",
        "help_type_confidence": 0.5,
        "expertise_match": [
          "skincare routine",
          "product recommendations",
          "vitamin c serum",
          "hair loss treatment",
          "curly hair care",
          "hair growth",
          "hair oils",
          "skincare",
          "haircare",
          "scientific",
          "product",
          "problem-solving"
        ],
        "response_angles": [
          "Recommend specific products you've used",
          "Suggest budget-friendly alternatives",
          "Share your experience with similar products"
        ],
        "urgency_level": "low",
        "competition_analysis": {
          "comment_count": 2,
          "engagement_level": "low",
          "response_opportunity": "good"
        },
        "confidence_score": 1.0,
        "response_suggestions": [
          "Moderate match for product_recommendation - share relevant experience and ask clarifying questions",
          "Your expertise in skincare routine, product recommendations is highly relevant",
          "Consider these approaches: Recommend specific products you've used, Suggest budget-friendly alternatives"
        ]
      }
    },
    {
      "id": "1rc7maw",
      "title": "Which pimple patch actually works the best?",
      "content": "Which of these pimple patch actually works? \n\nOr if you guys have any better suggestions, please do tell.\n\nAnd do they also help with the marks or only the pus/gunk?",
      "content_preview": "Which of these pimple patch actually works? \n\nOr if you guys have any better suggestions, please do tell.\n\nAnd do they also help with the marks or onl...",
      "content_length": 165,
      "subreddit": "IndianSkincareAddicts",
      "subreddit_color": "#ff4500",
      "subreddit_display": "r/IndianSkincareAddicts",
      "url": "https://reddit.com/r/IndianSkincareAddicts/comments/1rc7maw/which_pimple_patch_actually_works_the_best/",
      "score": 1,
      "comments": 3,
      "engagement_score": 4,
      "created_utc": 1771820482.0,
      "age_human": "26m ago",
      "age_seconds": 1570.029298067093,
      "author": "Visual-Razzmatazz658",
      "has_images": true,
      "image_urls": [
        {
          "url": "https://preview.redd.it/4z35i7xy76lg1.jpg?width=1284&format=pjpg&auto=webp&s=d162bc74f098e550de3e41d8ca005077a7d7ea99",
          "width": 1284,
          "height": 1524,
          "type": "gallery"
        },
        {
          "url": "https://preview.redd.it/ktp5m5xy76lg1.jpg?width=1284&format=pjpg&auto=webp&s=41fb7549152fd7025b3517ddaecdb89f8cc2ca0a",
          "width": 1284,
          "height": 1021,
          "type": "gallery"
        },
        {
          "url": "https://preview.redd.it/0d9p88xy76lg1.jpg?width=1284&format=pjpg&auto=webp&s=210a3f74b6a571cef761407d87a10b537039c5ae",
          "width": 1284,
          "height": 1384,
          "type": "gallery"
        }
      ],
      "image_count": 3,
      "flair": "I Followed Posting Rules",
      "is_self": false,
      "permalink": "/r/IndianSkincareAddicts/comments/1rc7maw/which_pimple_patch_actually_works_the_best/",
      "relevance_score": 100,
      "combined_score": 9.818285291310813,
      "engagement_score_original": 4,
      "opportunity_rating": "low",
      "context": {
        "triggered_keywords": [],
        "help_type": "product_recommendation",
        "help_type_confidence": 0.3,
        "expertise_match": [
          "vitamin c serum",
          "problem-solving"
        ],
        "response_angles": [
          "Recommend specific products you've used",
          "Suggest budget-friendly alternatives",
          "Share your experience with similar products"
        ],
        "urgency_level": "low",
        "competition_analysis": {
          "comment_count": 3,
          "engagement_level": "low",
          "response_opportunity": "good"
        },
        "confidence_score": 0.49,
        "response_suggestions": [
          "General match - provide helpful information and ask questions to understand their needs better",
          "Your expertise in vitamin c serum, problem-solving is highly relevant",
          "Consider these approaches: Recommend specific products you've used, Suggest budget-friendly alternatives"
        ]
      }
    },
    {
      "id": "1rc53c5",
      "title": "What hair fits me best",
      "content": "I’ve had some different hair lengths over the years I’m looking for what looks the best on me. Attached are pictures of the last 15 years. ",
      "content_preview": "I’ve had some different hair lengths over the years I’m looking for what looks the best on me. Attached are pictures of the last 15 years. ",
      "content_length": 139,
      "subreddit": "Hair",
      "subreddit_color": "#e74c3c",
      "subreddit_display": "r/Hair",
      "url": "https://reddit.com/r/Hair/comments/1rc53c5/what_hair_fits_me_best/",
      "score": 2,
      "comments": 21,
      "engagement_score": 23,
      "created_utc": 1771813191.0,
      "age_human": "2h ago",
      "age_seconds": 8861.02954697609,
      "author": "Similar-Afternoon-94",
      "has_images": true,
      "image_urls": [
        {
          "url": "https://preview.redd.it/gy6jv3jam5lg1.jpg?width=1320&format=pjpg&auto=webp&s=a29b4cca4ea42d591aad1a5142a8f1839265263e",
          "width": 1320,
          "height": 1357,
          "type": "gallery"
        },
        {
          "url": "https://preview.redd.it/s4fnd1jam5lg1.jpg?width=399&format=pjpg&auto=webp&s=740986f88ce93c06f314d5304fe7de5d68bb3b32",
          "width": 399,
          "height": 720,
          "type": "gallery"
        },
        {
          "url": "https://preview.redd.it/j9lws2jam5lg1.jpg?width=559&format=pjpg&auto=webp&s=91c4027e3108edaf7f0a35ff7020b15e6d3afd61",
          "width": 559,
          "height": 992,
          "type": "gallery"
        },
        {
          "url": "https://preview.redd.it/xj42n2jam5lg1.jpg?width=638&format=pjpg&auto=webp&s=22ca03c62752f5f0b763d92fc045544801ced0bd",
          "width": 638,
          "height": 1089,
          "type": "gallery"
        },
        {
          "url": "https://preview.redd.it/qg1dy0jam5lg1.jpg?width=1320&format=pjpg&auto=webp&s=eb41190bfc71117ea3e739a6bcb8d51d09d9eb3c",
          "width": 1320,
          "height": 488,
          "type": "gallery"
        },
        {
          "url": "https://preview.redd.it/8zq2x9jam5lg1.jpg?width=3024&format=pjpg&auto=webp&s=340c2f574ff21ee787b55eef57ea13495e078fc7",
          "width": 3024,
          "height": 4032,
          "type": "gallery"
        },
        {
          "url": "https://preview.redd.it/ksprodjam5lg1.jpg?width=2316&format=pjpg&auto=webp&s=1c4b846a4b0e253882e9784fce81f64a68639071",
          "width": 2316,
          "height": 3088,
          "type": "gallery"
        },
        {
          "url": "https://preview.redd.it/3qpqe5jam5lg1.jpg?width=1290&format=pjpg&auto=webp&s=e769f1468cd4ef7fa1fdc97235914d97090f3c58",
          "width": 1290,
          "height": 1720,
          "type": "gallery"
        }
      ],
      "image_count": 8,
      "flair": "Help",
      "is_self": false,
      "permalink": "/r/Hair/comments/1rc53c5/what_hair_fits_me_best/",
      "relevance_score": 100,
      "combined_score": 9.564186130728986,
      "engagement_score_original": 23,
      "opportunity_rating": "low",
      "context": {
        "triggered_keywords": [],
        "help_type": "product_recommendation",
        "help_type_confidence": 0.1,
        "expertise_match": [
          "vitamin c serum",
          "hair loss treatment",
          "curly hair care",
          "hair growth",
          "hair oils",
          "haircare"
        ],
        "response_angles": [
          "Recommend specific products you've used",
          "Suggest budget-friendly alternatives",
          "Share your experience with similar products"
        ],
        "urgency_level": "low",
        "competition_analysis": {
          "comment_count": 21,
          "engagement_level": "high",
          "response_opportunity": "limited"
        },
        "confidence_score": 1.0,
        "response_suggestions": [
          "General match - provide helpful information and ask questions to understand their needs better",
          "Your expertise in vitamin c serum, hair loss treatment is highly relevant",
          "Consider these approaches: Recommend specific products you've used, Suggest budget-friendly alternatives"
        ]
      }
    },
    {
      "id": "1rc30vj",
      "title": "How to style my hair?",
      "content": "I have no idea to style my hair curly. I’m getting it dyed hot pink and black next week. Do you have any recommendations for hairstyles I could do? I use curl cream and hair oil currently. ",
      "content_preview": "I have no idea to style my hair curly. I’m getting it dyed hot pink and black next week. Do you have any recommendations for hairstyles I could do? I ...",
      "content_length": 189,
      "subreddit": "Hair",
      "subreddit_color": "#e74c3c",
      "subreddit_display": "r/Hair",
      "url": "https://reddit.com/r/Hair/comments/1rc30vj/how_to_style_my_hair/",
      "score": 1,
      "comments": 2,
      "engagement_score": 3,
      "created_utc": 1771807532.0,
      "age_human": "4h ago",
      "age_seconds": 14520.029819011688,
      "author": "Latter-Variation-909",
      "has_images": true,
      "image_urls": [
        {
          "url": "https://preview.redd.it/06b9m4qg55lg1.jpg?width=4032&format=pjpg&auto=webp&s=c7e39fe8bcbb04b74324c2c6c637f26a6bac67b9",
          "width": 4032,
          "height": 3024,
          "type": "gallery"
        },
        {
          "url": "https://preview.redd.it/5uhwo1qg55lg1.jpg?width=4032&format=pjpg&auto=webp&s=25f3a9a7427ed58d787256940545768d247b6ff3",
          "width": 4032,
          "height": 3024,
          "type": "gallery"
        }
      ],
      "image_count": 2,
      "flair": "Help",
      "is_self": false,
      "permalink": "/r/Hair/comments/1rc30vj/how_to_style_my_hair/",
      "relevance_score": 100,
      "combined_score": 9.48416362203492,
      "engagement_score_original": 3,
      "opportunity_rating": "low",
      "context": {
        "triggered_keywords": [
          "hair oil"
        ],
        "help_type": "hair_concern",
        "help_type_confidence": 0.2,
        "expertise_match": [
          "product recommendations",
          "vitamin c serum",
          "hair loss treatment",
          "curly hair care",
          "hair growth",
          "hair oils",
          "haircare",
          "product"
        ],
        "response_angles": [
          "Share your hair care experience",
          "Suggest products for their hair type",
          "Recommend professional consultation if needed"
        ],
        "urgency_level": "low",
        "competition_analysis": {
          "comment_count": 2,
          "engagement_level": "low",
          "response_opportunity": "good"
        },
        "confidence_score": 1.0,
        "response_suggestions": [
          "General match - provide helpful information and ask questions to understand their needs better",
          "Your expertise in product recommendations, vitamin c serum is highly relevant",
          "Consider these approaches: Share your hair care experience, Suggest products for their hair type"
        ]
      }
    },
    {
      "id": "1rc7lcd",
      "title": "Help me select a pimple patch",
      "content": "Which of these pimple patch actually works? \n\nOr if you guys have any better suggestions, please do tell.\n\nAnd do they also help with the marks or only the pus/gunk?",
      "content_preview": "Which of these pimple patch actually works? \n\nOr if you guys have any better suggestions, please do tell.\n\nAnd do they also help with the marks or onl...",
      "content_length": 165,
      "subreddit": "IndianSkincareAddicts",
      "subreddit_color": "#ff4500",
      "subreddit_display": "r/IndianSkincareAddicts",
      "url": "https://reddit.com/r/IndianSkincareAddicts/comments/1rc7lcd/help_me_select_a_pimple_patch/",
      "score": 1,
      "comments": 2,
      "engagement_score": 3,
      "created_utc": 1771820404.0,
      "age_human": "27m ago",
      "age_seconds": 1648.0300869941711,
      "author": "Visual-Razzmatazz658",
      "has_images": true,
      "image_urls": [
        {
          "url": "https://preview.redd.it/d02dd3jq76lg1.jpg?width=1284&format=pjpg&auto=webp&s=3f7e7c0d7660b37a1ba3ea6e11638140f4502cf3",
          "width": 1284,
          "height": 1524,
          "type": "gallery"
        },
        {
          "url": "https://preview.redd.it/4b5wv0jq76lg1.jpg?width=1284&format=pjpg&auto=webp&s=37aaf631c2f7f6f6cbb0cd3ecd86b3a3bc4bd30b",
          "width": 1284,
          "height": 1021,
          "type": "gallery"
        },
        {
          "url": "https://preview.redd.it/lkkf73jq76lg1.jpg?width=1284&format=pjpg&auto=webp&s=58d297bf53d789e73acbf78c817f03afa9e2e800",
          "width": 1284,
          "height": 1384,
          "type": "gallery"
        }
      ],
      "image_count": 3,
      "flair": "I Followed Posting Rules",
      "is_self": false,
      "permalink": "/r/IndianSkincareAddicts/comments/1rc7lcd/help_me_select_a_pimple_patch/",
      "relevance_score": 100,
      "combined_score": 9.41688720978631,
      "engagement_score_original": 3,
      "opportunity_rating": "low",
      "context": {
        "triggered_keywords": [],
        "help_type": "troubleshooting",
        "help_type_confidence": 0.3,
        "expertise_match": [
          "vitamin c serum",
          "problem-solving"
        ],
        "response_angles": [
          "Share how you solved a similar problem",
          "Suggest diagnostic questions to ask",
          "Recommend gentle solutions to try first"
        ],
        "urgency_level": "low",
        "competition_analysis": {
          "comment_count": 2,
          "engagement_level": "low",
          "response_opportunity": "good"
        },
        "confidence_score": 0.49,
        "response_suggestions": [
          "General match - provide helpful information and ask questions to understand their needs better",
          "Your expertise in vitamin c serum, problem-solving is highly relevant",
          "Consider these approaches: Share how you solved a similar problem, Suggest diagnostic questions to ask"
        ]
      }
    },
    {
      "id": "1rc67iu",
      "title": "[Routine Help] Thoughts on my new routine?",
      "content": "Hello lovelies\n\nI’ve struggled a lot with my skin in the last 5 months especially after a hefty medication change and withdrawals. Following this, I dragged myself through the awful cycle of dermatillomania over and over. It’s been getting me down a lot and I’m becoming increasingly self conscious about it.  I’ve made the push to buy some skincare products to try and look after my skin better now. I have high hopes that I’ll be motivated to keep a new routine:)\n\nI have combination skin and I’m quite sensitive, I easily rash up etc. I did patch tests when my new skincare arrived a few days ago, to get an idea on if my skin can tolerate it. So far so good! \n\nI’ve just done night 1 with my new products. I was wondering if anyone can confirm if these are ‘okay’ products to use and if my order of usage is correct? Of course, I understand routines are different for everyone. I just wanted to check I’m not making a big mistake somewhere.\n\nMy products:\n\nCereVe - Blemish Control Cleanser \n\nAveeno - Nourishing Oat Cleanser\n\nByoma - Hydrating Milk Toner \n\nThe Ordinary - Hyaluronic Acid 2% + B5\n\nThe Ordinary - Niacinamide 10% + Zinc 1%\n\nThe Ordinary - Natural Moisturising Factors + HA\n\nThe Ordinary - Sulfur 10% Powder to Cream Concentrate \n\nAs far as I have read, the CereVe can be a harsh exfoliant so I plan to use this once every 2 nights if not less. Everything else I plan on using every night (and morning?), just starting with the Aveeno cleanser. \n\nMy routine (including the CereVe):\n\n1. CereVe cleanser (wash off) \n\n2. Aveeno Oat cleanser (wash off)\n\n3. Byoma toner \n\n4. While toner is still wet, apply Hyaluronic acid serum \n\n5. Wait a minute or two, then apply Niacinamide serum\n\n6. Once fully absorbed, apply moisturiser \n\nI’m unsure when to apply the sulfer concentrate (which I’d apply only on my spots). As in - which step should it be? I skipped using it for my first night of the new routine as I wasn’t sure.\n\nI looked extensively into what products should be compatible with my skin, and the products listed are the ones I decided on. I don’t wear much make up at all - usually just concealer and mascara, although I’ve avoided even wearing concealer the last month (ish) in order to try and help my skin a bit. \n\nI’m pretty excited to form a new routine and hopefully see an improvement:)\n\nI’d love to hear any advice and/or experiences others have had with these products.\n\nThanks so much!",
      "content_preview": "Hello lovelies\n\nI’ve struggled a lot with my skin in the last 5 months especially after a hefty medication change and withdrawals. Following this, I d...",
      "content_length": 2418,
      "subreddit": "SkincareAddiction",
      "subreddit_color": "#7193ff",
      "subreddit_display": "r/SkincareAddiction",
      "url": "https://reddit.com/r/SkincareAddiction/comments/1rc67iu/routine_help_thoughts_on_my_new_routine/",
      "score": 1,
      "comments": 3,
      "engagement_score": 4,
      "created_utc": 1771816318.0,
      "age_human": "1h ago",
      "age_seconds": 5734.030337095261,
      "author": "Cute_Clock_788",
      "has_images": true,
      "image_urls": [
        {
          "url": "https://preview.redd.it/67tkviokv5lg1.jpg?width=3024&format=pjpg&auto=webp&s=c82a486ade644c4cce6db93ddd2e42da0f19cf73",
          "width": 3024,
          "height": 4032,
          "type": "gallery"
        },
        {
          "url": "https://preview.redd.it/tayh6jokv5lg1.jpg?width=3024&format=pjpg&auto=webp&s=90ca82e2aa6fe20261798334da36310748f64b3f",
          "width": 3024,
          "height": 2851,
          "type": "gallery"
        },
        {
          "url": "https://preview.redd.it/thphelokv5lg1.jpg?width=2916&format=pjpg&auto=webp&s=160858e8ea316e7b51a6fca18f66f21713a2ae97",
          "width": 2916,
          "height": 3467,
          "type": "gallery"
        },
        {
          "url": "https://preview.redd.it/r1y5s6okv5lg1.jpg?width=1179&format=pjpg&auto=webp&s=0c748fb7a0a08d5d26dfa53e8165235f3e94af0e",
          "width": 1179,
          "height": 2051,
          "type": "gallery"
        },
        {
          "url": "https://preview.redd.it/v9vis5okv5lg1.jpg?width=1179&format=pjpg&auto=webp&s=2a1579f5d33f29232727d0a6ee6050a76d311562",
          "width": 1179,
          "height": 1834,
          "type": "gallery"
        },
        {
          "url": "https://preview.redd.it/u6kq7fokv5lg1.jpg?width=1179&format=pjpg&auto=webp&s=0f53a9b91278f02c2f63b945dcf314222e05ca1c",
          "width": 1179,
          "height": 2025,
          "type": "gallery"
        }
      ],
      "image_count": 6,
      "flair": "Routine Help",
      "is_self": false,
      "permalink": "/r/SkincareAddiction/comments/1rc67iu/routine_help_thoughts_on_my_new_routine/",
      "relevance_score": 100,
      "combined_score": 9.33634065243381,
      "engagement_score_original": 4,
      "opportunity_rating": "low",
      "context": {
        "triggered_keywords": [
          "combination skin",
          "routine",
          "hyaluronic acid",
          "skincare",
          "products",
          "niacinamide"
        ],
        "help_type": "routine_help",
        "help_type_confidence": 0.7,
        "expertise_match": [
          "skincare routine",
          "product recommendations",
          "sensitive skin",
          "niacinamide",
          "vitamin c serum",
          "skin barrier repair",
          "salicylic acid",
          "hyaluronic acid",
          "curly hair care",
          "skincare",
          "ingredients",
          "product",
          "problem-solving"
        ],
        "response_angles": [
          "Share your personal routine experience",
          "Suggest a step-by-step routine based on their skin type",
          "Recommend products for each step"
        ],
        "urgency_level": "low",
        "competition_analysis": {
          "comment_count": 3,
          "engagement_level": "low",
          "response_opportunity": "good"
        },
        "confidence_score": 1.0,
        "response_suggestions": [
          "Moderate match for routine_help - share relevant experience and ask clarifying questions",
          "Your expertise in skincare routine, product recommendations is highly relevant",
          "Consider these approaches: Share your personal routine experience, Suggest a step-by-step routine based on their skin type"
        ]
      }
    },
    {
      "id": "1rc2gw6",
      "title": "Looking for a product to help with cellulite, preferably under $50USD",
      "content": "I (19f) have always had a lot of cellulite on my thighs and it's something that I've always been somewhat insecure about. I know you can't make it go away completely, but does anyone have any good recommendations for minimizing the appearance of cellulite? I am open to trying new products, but would prefer to spend under $50 as I am a broke college student",
      "content_preview": "I (19f) have always had a lot of cellulite on my thighs and it's something that I've always been somewhat insecure about. I know you can't make it go ...",
      "content_length": 358,
      "subreddit": "beauty",
      "subreddit_color": "#f39c12",
      "subreddit_display": "r/beauty",
      "url": "https://reddit.com/r/beauty/comments/1rc2gw6/looking_for_a_product_to_help_with_cellulite/",
      "score": 0,
      "comments": 3,
      "engagement_score": 3,
      "created_utc": 1771806088.0,
      "age_human": "4h ago",
      "age_seconds": 15964.031327962875,
      "author": "FOB_cures_my_sadness",
      "has_images": false,
      "image_urls": [],
      "image_count": 0,
      "flair": "Seeking Advice",
      "is_self": true,
      "permalink": "/r/beauty/comments/1rc2gw6/looking_for_a_product_to_help_with_cellulite/",
      "relevance_score": 100,
      "combined_score": 9.293635795308482,
      "engagement_score_original": 3,
      "opportunity_rating": "low",
      "context": {
        "triggered_keywords": [
          "products"
        ],
        "help_type": "product_recommendation",
        "help_type_confidence": 0.6,
        "expertise_match": [
          "product recommendations",
          "vitamin c serum",
          "product",
          "problem-solving"
        ],
        "response_angles": [
          "Recommend specific products you've used",
          "Suggest budget-friendly alternatives",
          "Share your experience with similar products"
        ],
        "urgency_level": "low",
        "competition_analysis": {
          "comment_count": 3,
          "engagement_level": "low",
          "response_opportunity": "good"
        },
        "confidence_score": 1.0,
        "response_suggestions": [
          "Moderate match for product_recommendation - share relevant experience and ask clarifying questions",
          "Your expertise in product recommendations, vitamin c serum is highly relevant",
          "Consider these approaches: Recommend specific products you've used, Suggest budget-friendly alternatives"
        ]
      }
    },
    {
      "id": "1rc7ntu",
      "title": "Help with tan and darkness on eyelids",
      "content": "My forehead is darker than my cheeks and chin also the darkness around eyelids and inner corner of the eyes are getting bad now. \n\n\nI'm using dermatologist suggested routine only. \n\nI've oily acne prone sensitive skin \n\nAM routine -\nAcmed face wash, physiogel moisturizer and boj sunscreen \n\nPM routine - \nAcmed face wash, acnewar gel (adapalene), physiogel moisturizer \n\n\nUsed boj eye cream it didn't work and triggered my acne. So stopped using it. \nPlease suggest something for forehead asap 🙃\nI've 3 months of time to my bestie's marriage. \nThank you in advance 🫶",
      "content_preview": "My forehead is darker than my cheeks and chin also the darkness around eyelids and inner corner of the eyes are getting bad now. \n\n\nI'm using dermatol...",
      "content_length": 567,
      "subreddit": "IndianSkincareAddicts",
      "subreddit_color": "#ff4500",
      "subreddit_display": "r/IndianSkincareAddicts",
      "url": "https://reddit.com/r/IndianSkincareAddicts/comments/1rc7ntu/help_with_tan_and_darkness_on_eyelids/",
      "score": 1,
      "comments": 6,
      "engagement_score": 7,
      "created_utc": 1771820612.0,
      "age_human": "24m ago",
      "age_seconds": 1440.0316309928894,
      "author": "Unique_Rip7422",
      "has_images": true,
      "image_urls": [
        {
          "url": "https://preview.redd.it/pqak54uc86lg1.png?auto=webp&s=08c20c7d502e88c9f1fb2a400fb5cf909a253c42",
          "width": 1080,
          "height": 688,
          "type": "preview"
        }
      ],
      "image_count": 1,
      "flair": "I Followed Posting Rules",
      "is_self": false,
      "permalink": "/r/IndianSkincareAddicts/comments/1rc7ntu/help_with_tan_and_darkness_on_eyelids/",
      "relevance_score": 100,
      "combined_score": 9.243331695852456,
      "engagement_score_original": 7,
      "opportunity_rating": "low",
      "context": {
        "triggered_keywords": [
          "routine",
          "acne",
          "sunscreen",
          "sensitive skin"
        ],
        "help_type": "troubleshooting",
        "help_type_confidence": 0.3,
        "expertise_match": [
          "skincare routine",
          "acne treatment",
          "sensitive skin",
          "vitamin c serum",
          "skin barrier repair",
          "pH balance",
          "sunscreen",
          "skincare",
          "problem-solving"
        ],
        "response_angles": [
          "Share how you solved a similar problem",
          "Suggest diagnostic questions to ask",
          "Recommend gentle solutions to try first"
        ],
        "urgency_level": "high",
        "competition_analysis": {
          "comment_count": 6,
          "engagement_level": "medium",
          "response_opportunity": "moderate"
        },
        "confidence_score": 1.0,
        "response_suggestions": [
          "General match - provide helpful information and ask questions to understand their needs better",
          "Your expertise in skincare routine, acne treatment is highly relevant",
          "Consider these approaches: Share how you solved a similar problem, Suggest diagnostic questions to ask"
        ]
      }
    },
    {
      "id": "1rc55zc",
      "title": "Please help, product recommendations and advice",
      "content": "Please help a person out😭\n\nRoutine:\n\nI use Ouidad Defrizzing Shampoo and Conditioner. I also use their conditioning mask, and Heat &amp; Humidity gel. I wash my hair every 3ish days as my hair tends to be very clean. I used to sleep in a bonnet but I get tension headaches so I sleep on a stain pillow case.\n\nI just can't understand why my hair is so flat on the back and sides. (Current hair is short like every image but last three). It keeps its shape well (unless sleeping). Image 7 is after it dried with a headband on. Kept the shape for the whole day. I just want my hair to be defined and voluminous. Images 1-4 are how my hair dried after my shower (diffused and air dried). Images 5&amp;6 are how I usually have it (little to no gel and we're taken before wash day) Images 8&amp;9 are showing what my texture looked like longer.\n\nI am the only one with textured hair in my family please send help😭",
      "content_preview": "Please help a person out😭\n\nRoutine:\n\nI use Ouidad Defrizzing Shampoo and Conditioner. I also use their conditioning mask, and Heat &amp; Humidity gel....",
      "content_length": 907,
      "subreddit": "curlyhair",
      "subreddit_color": "#ff6b35",
      "subreddit_display": "r/curlyhair",
      "url": "https://reddit.com/r/curlyhair/comments/1rc55zc/please_help_product_recommendations_and_advice/",
      "score": 2,
      "comments": 1,
      "engagement_score": 3,
      "created_utc": 1771813401.0,
      "age_human": "2h ago",
      "age_seconds": 8651.032006025314,
      "author": "Jun1m0",
      "has_images": true,
      "image_urls": [
        {
          "url": "https://preview.redd.it/zvww8k5vm5lg1.jpg?width=3000&format=pjpg&auto=webp&s=420ebbaca767667cd677260f9b54878177cbb233",
          "width": 3000,
          "height": 4000,
          "type": "gallery"
        },
        {
          "url": "https://preview.redd.it/700zfghvm5lg1.jpg?width=3000&format=pjpg&auto=webp&s=2ad6f6143a6ec6d7bd3cd04d5fef1f8eda33a103",
          "width": 3000,
          "height": 4000,
          "type": "gallery"
        },
        {
          "url": "https://preview.redd.it/chvys7wvm5lg1.jpg?width=1798&format=pjpg&auto=webp&s=da35cd7c277357a189ef79e4906e91facb72d2e7",
          "width": 1798,
          "height": 2398,
          "type": "gallery"
        },
        {
          "url": "https://preview.redd.it/6hze0r0wm5lg1.jpg?width=1786&format=pjpg&auto=webp&s=561768f2376015e34e5da263b2a8f88821c80b4e",
          "width": 1786,
          "height": 2380,
          "type": "gallery"
        },
        {
          "url": "https://preview.redd.it/cyklv06wm5lg1.jpg?width=2544&format=pjpg&auto=webp&s=2a8a08d20719109456da67e48df15cae9c6712ef",
          "width": 2544,
          "height": 3392,
          "type": "gallery"
        },
        {
          "url": "https://preview.redd.it/kkklxjfwm5lg1.jpg?width=2544&format=pjpg&auto=webp&s=232e7ed8ba8880633e8ac4bfab4cd398fe4e2bfc",
          "width": 2544,
          "height": 3392,
          "type": "gallery"
        },
        {
          "url": "https://preview.redd.it/b16tnhowm5lg1.jpg?width=3000&format=pjpg&auto=webp&s=9ba52f3761520fe80fe6915cff1c134448434105",
          "width": 3000,
          "height": 4000,
          "type": "gallery"
        },
        {
          "url": "https://preview.redd.it/5qodarywm5lg1.jpg?width=1080&format=pjpg&auto=webp&s=c1412ae2ad6f956a6658c390b88f56bc5a916426",
          "width": 1080,
          "height": 1440,
          "type": "gallery"
        },
        {
          "url": "https://preview.redd.it/p8l5bu1xm5lg1.jpg?width=1080&format=pjpg&auto=webp&s=bcccb66472a713d0645030d4908bc4477fd87ce7",
          "width": 1080,
          "height": 1434,
          "type": "gallery"
        }
      ],
      "image_count": 9,
      "flair": "Help!",
      "is_self": false,
      "permalink": "/r/curlyhair/comments/1rc55zc/please_help_product_recommendations_and_advice/",
      "relevance_score": 100,
      "combined_score": 8.638775618447198,
      "engagement_score_original": 3,
      "opportunity_rating": "low",
      "context": {
        "triggered_keywords": [
          "texture",
          "shampoo",
          "routine",
          "conditioner",
          "product recommendations"
        ],
        "help_type": "product_recommendation",
        "help_type_confidence": 0.2,
        "expertise_match": [
          "skincare routine",
          "product recommendations",
          "vitamin c serum",
          "hair loss treatment",
          "curly hair care",
          "hair growth",
          "hair oils",
          "skincare",
          "haircare",
          "product",
          "problem-solving"
        ],
        "response_angles": [
          "Recommend specific products you've used",
          "Suggest budget-friendly alternatives",
          "Share your experience with similar products"
        ],
        "urgency_level": "low",
        "competition_analysis": {
          "comment_count": 1,
          "engagement_level": "low",
          "response_opportunity": "good"
        },
        "confidence_score": 1.0,
        "response_suggestions": [
          "General match - provide helpful information and ask questions to understand their needs better",
          "Your expertise in skincare routine, product recommendations is highly relevant",
          "Consider these approaches: Recommend specific products you've used, Suggest budget-friendly alternatives"
        ]
      }
    },
    {
      "id": "1rc2eku",
      "title": "What hair colour? Wanted to go younger and thinner but didn’t work out.",
      "content": "I've never been a fan of having my picture taken (never felt pretty enough to be comfortable with it), so the images are probably not that good. I HAVE been a fan of changing the colour of my hair though.\n\nUsually, I go back to being blonde. Last summer I was blonde, got some pink going (no pictures of me with that), and then went copper. As fall faded I started going blonder before trying silver grey over new years. Currently, I am very light faded blonde.\n\nI have a new job starting soon (brand manager for a beauty wholesaler) and am considering my next haircolour.\n\nThe images are in a timeline, first from 2019 (hair half brushed dry before a hair dye) and the most recent is recent. Should I go darker, lighter, keep it?\n\nI would love to have the curly hair I have going at one point, but it's so time consuming and I have a job, home and child to take care of.",
      "content_preview": "I've never been a fan of having my picture taken (never felt pretty enough to be comfortable with it), so the images are probably not that good. I HAV...",
      "content_length": 871,
      "subreddit": "beauty",
      "subreddit_color": "#f39c12",
      "subreddit_display": "r/beauty",
      "url": "https://reddit.com/r/beauty/comments/1rc2eku/what_hair_colour_wanted_to_go_younger_and_thinner/",
      "score": 12,
      "comments": 34,
      "engagement_score": 46,
      "created_utc": 1771805921.0,
      "age_human": "4h ago",
      "age_seconds": 16131.03253698349,
      "author": "teacuptrooper",
      "has_images": true,
      "image_urls": [
        {
          "url": "https://preview.redd.it/m0vtzzpn05lg1.jpg?width=2320&format=pjpg&auto=webp&s=117f36621e8aa35ffefa903c13ef46f8376d70e3",
          "width": 2320,
          "height": 3088,
          "type": "gallery"
        },
        {
          "url": "https://preview.redd.it/wqo9hzpn05lg1.jpg?width=3024&format=pjpg&auto=webp&s=a99fc73cc9879921f525f5b2d4b778e8c3610f3c",
          "width": 3024,
          "height": 4032,
          "type": "gallery"
        },
        {
          "url": "https://preview.redd.it/8xs6lnqn05lg1.jpg?width=2320&format=pjpg&auto=webp&s=694d6934212b69c862a19fb092b5427bce7d9e9f",
          "width": 2320,
          "height": 3088,
          "type": "gallery"
        },
        {
          "url": "https://preview.redd.it/7o0ybnqn05lg1.jpg?width=2316&format=pjpg&auto=webp&s=ed5e24e18c4529741f12df5e737ba732fb4362b1",
          "width": 2316,
          "height": 3088,
          "type": "gallery"
        },
        {
          "url": "https://preview.redd.it/vjszsmqn05lg1.jpg?width=3024&format=pjpg&auto=webp&s=89627f5a89e9c58f9cab4ae82e3c42f7ccee7f06",
          "width": 3024,
          "height": 4032,
          "type": "gallery"
        },
        {
          "url": "https://preview.redd.it/jvgbjnqn05lg1.jpg?width=862&format=pjpg&auto=webp&s=55fcaa6f8a29c72128abcdfbca9780f8b358aa0f",
          "width": 862,
          "height": 1388,
          "type": "gallery"
        },
        {
          "url": "https://preview.redd.it/8yebbpqn05lg1.jpg?width=1080&format=pjpg&auto=webp&s=f715f5447f3841c0ff2f9ec5388d521f5e5e5c20",
          "width": 1080,
          "height": 1920,
          "type": "gallery"
        },
        {
          "url": "https://preview.redd.it/jhfkvzpn05lg1.jpg?width=1691&format=pjpg&auto=webp&s=7c642ca7dde2524c79045bfca9682b12459fe5b2",
          "width": 1691,
          "height": 2433,
          "type": "gallery"
        },
        {
          "url": "https://preview.redd.it/0mafinqn05lg1.jpg?width=2316&format=pjpg&auto=webp&s=c8878cbe852dd16e3bc594904f63052f9ed840c0",
          "width": 2316,
          "height": 3088,
          "type": "gallery"
        },
        {
          "url": "https://preview.redd.it/n0pfy3qn05lg1.jpg?width=3024&format=pjpg&auto=webp&s=2a9c756031b63d00aab8335b8159e3803f6802c1",
          "width": 3024,
          "height": 4032,
          "type": "gallery"
        },
        {
          "url": "https://preview.redd.it/1612enqn05lg1.jpg?width=2316&format=pjpg&auto=webp&s=0f0690852cae6915bf11f2f62239b025da8691e2",
          "width": 2316,
          "height": 3088,
          "type": "gallery"
        },
        {
          "url": "https://preview.redd.it/hl2ka5qn05lg1.jpg?width=3024&format=pjpg&auto=webp&s=b83619507066421e9ab770dd27b482a83b6ef354",
          "width": 3024,
          "height": 4032,
          "type": "gallery"
        },
        {
          "url": "https://preview.redd.it/g1mrvzpn05lg1.jpg?width=2316&format=pjpg&auto=webp&s=0545192ea7dd5d45a2fc10651cd8eab25afb5e86",
          "width": 2316,
          "height": 3088,
          "type": "gallery"
        },
        {
          "url": "https://preview.redd.it/rv2cd7qn05lg1.jpg?width=3024&format=pjpg&auto=webp&s=ba7d34364102f4c3501e02fbf89a9fb35b12e78e",
          "width": 3024,
          "height": 4032,
          "type": "gallery"
        },
        {
          "url": "https://preview.redd.it/a00jxpqn05lg1.jpg?width=2216&format=pjpg&auto=webp&s=e8db5ee407799e821357996d87fba6822aad0db2",
          "width": 2216,
          "height": 2648,
          "type": "gallery"
        }
      ],
      "image_count": 15,
      "flair": "Seeking Advice",
      "is_self": false,
      "permalink": "/r/beauty/comments/1rc2eku/what_hair_colour_wanted_to_go_younger_and_thinner/",
      "relevance_score": 100,
      "combined_score": 8.392563452218418,
      "engagement_score_original": 46,
      "opportunity_rating": "low",
      "context": {
        "triggered_keywords": [
          "beauty",
          "curly hair"
        ],
        "help_type": "hair_concern",
        "help_type_confidence": 0.2,
        "expertise_match": [
          "vitamin c serum",
          "hair loss treatment",
          "curly hair care",
          "hair growth",
          "hair oils",
          "haircare",
          "product"
        ],
        "response_angles": [
          "Share your hair care experience",
          "Suggest products for their hair type",
          "Recommend professional consultation if needed"
        ],
        "urgency_level": "medium",
        "competition_analysis": {
          "comment_count": 34,
          "engagement_level": "high",
          "response_opportunity": "limited"
        },
        "confidence_score": 1.0,
        "response_suggestions": [
          "General match - provide helpful information and ask questions to understand their needs better",
          "Your expertise in vitamin c serum, hair loss treatment is highly relevant",
          "Consider these approaches: Share your hair care experience, Suggest products for their hair type"
        ]
      }
    },
    {
      "id": "1rc76yi",
      "title": "I know this isn't the best way to decide but I'm in a hurry, I have a friends bachelorette party in a little bit, backs broken out, can't wear my hair up like I wanted. Leave it straight or wavy or loose curls? Going to a mid-high end restaurant/bar, plz help.",
      "content": "",
      "content_preview": "",
      "content_length": 0,
      "subreddit": "Hair",
      "subreddit_color": "#e74c3c",
      "subreddit_display": "r/Hair",
      "url": "https://reddit.com/r/Hair/comments/1rc76yi/i_know_this_isnt_the_best_way_to_decide_but_im_in/",
      "score": 1,
      "comments": 4,
      "engagement_score": 5,
      "created_utc": 1771819201.0,
      "age_human": "47m ago",
      "age_seconds": 2851.033080101013,
      "author": "FastyNilthShreakyFit",
      "has_images": true,
      "image_urls": [
        {
          "url": "https://preview.redd.it/188ldcu546lg1.jpg?width=1242&format=pjpg&auto=webp&s=4c07f7afc92e8f9d42dac5aec1cc414f2747b4e1",
          "width": 1242,
          "height": 1635,
          "type": "gallery"
        },
        {
          "url": "https://preview.redd.it/y402mcu546lg1.jpg?width=1242&format=pjpg&auto=webp&s=91289812850797758968321c20304510f0081801",
          "width": 1242,
          "height": 1408,
          "type": "gallery"
        }
      ],
      "image_count": 2,
      "flair": "Help",
      "is_self": false,
      "permalink": "/r/Hair/comments/1rc76yi/i_know_this_isnt_the_best_way_to_decide_but_im_in/",
      "relevance_score": 100,
      "combined_score": 8.31621767012223,
      "engagement_score_original": 5,
      "opportunity_rating": "low",
      "context": {
        "triggered_keywords": [],
        "help_type": "hair_concern",
        "help_type_confidence": 0.2,
        "expertise_match": [
          "vitamin c serum",
          "hair loss treatment",
          "curly hair care",
          "hair growth",
          "hair oils",
          "haircare",
          "problem-solving"
        ],
        "response_angles": [
          "Share your hair care experience",
          "Suggest products for their hair type",
          "Recommend professional consultation if needed"
        ],
        "urgency_level": "low",
        "competition_analysis": {
          "comment_count": 4,
          "engagement_level": "medium",
          "response_opportunity": "good"
        },
        "confidence_score": 1.0,
        "response_suggestions": [
          "General match - provide helpful information and ask questions to understand their needs better",
          "Your expertise in vitamin c serum, hair loss treatment is highly relevant",
          "Consider these approaches: Share your hair care experience, Suggest products for their hair type"
        ]
      }
    },
    {
      "id": "1rbva2u",
      "title": "Trying to grow it out, but I have no idea what products to use or how to style it. It's a disaster, what should I do?",
      "content": "The pictures show my hair when dry and when brushed with a homemade anti-frizz oil. That is very much all I do, other than wash it 2 times a week with a shower gel. I have of course read and know that thick and curly hair like mine should not be brushed, but I kind of have no choice other than to bursh it because I just don't know what else to do. I don't use conditioner, no cream, my routine is just:\n\n1. Get it wet every day in the shower  \n2. Dry the ends with a towel and brush it with anti-frizz oil  \n3. The rest of the hair I just let it wet  \n4. I do use a silk pillowcase. I'm not sure it does much to help, though.\n\nAs I've said, everything I use is homemade. I do not use traditional shampoo at the current moment due to skin issues that can be slightly seen on the pictures, but I am willing to try it out. I would appreciate any help.",
      "content_preview": "The pictures show my hair when dry and when brushed with a homemade anti-frizz oil. That is very much all I do, other than wash it 2 times a week with...",
      "content_length": 850,
      "subreddit": "curlyhair",
      "subreddit_color": "#ff6b35",
      "subreddit_display": "r/curlyhair",
      "url": "https://reddit.com/r/curlyhair/comments/1rbva2u/trying_to_grow_it_out_but_i_have_no_idea_what/",
      "score": 3,
      "comments": 5,
      "engagement_score": 8,
      "created_utc": 1771789115.0,
      "age_human": "9h ago",
      "age_seconds": 32937.033376932144,
      "author": "Salty-Subject9559",
      "has_images": true,
      "image_urls": [
        {
          "url": "https://preview.redd.it/3foy7wwnm3lg1.jpg?width=960&format=pjpg&auto=webp&s=074d68f3643095fd186661c714be342114a86bb2",
          "width": 960,
          "height": 720,
          "type": "gallery"
        },
        {
          "url": "https://preview.redd.it/lparbluom3lg1.jpg?width=960&format=pjpg&auto=webp&s=a1e77171b96332badd1b8908b3f43d8fc8c4d884",
          "width": 960,
          "height": 720,
          "type": "gallery"
        }
      ],
      "image_count": 2,
      "flair": "Help!",
      "is_self": false,
      "permalink": "/r/curlyhair/comments/1rbva2u/trying_to_grow_it_out_but_i_have_no_idea_what/",
      "relevance_score": 100,
      "combined_score": 8.291712143684979,
      "engagement_score_original": 8,
      "opportunity_rating": "low",
      "context": {
        "triggered_keywords": [
          "curly hair",
          "shampoo",
          "routine",
          "conditioner",
          "products"
        ],
        "help_type": "routine_help",
        "help_type_confidence": 0.5,
        "expertise_match": [
          "skincare routine",
          "product recommendations",
          "sensitive skin",
          "vitamin c serum",
          "skin barrier repair",
          "hair loss treatment",
          "curly hair care",
          "hair growth",
          "hair oils",
          "skincare",
          "haircare",
          "product",
          "problem-solving"
        ],
        "response_angles": [
          "Share your personal routine experience",
          "Suggest a step-by-step routine based on their skin type",
          "Recommend products for each step"
        ],
        "urgency_level": "low",
        "competition_analysis": {
          "comment_count": 5,
          "engagement_level": "medium",
          "response_opportunity": "moderate"
        },
        "confidence_score": 1.0,
        "response_suggestions": [
          "Moderate match for routine_help - share relevant experience and ask clarifying questions",
          "Your expertise in skincare routine, product recommendations is highly relevant",
          "Consider these approaches: Share your personal routine experience, Suggest a step-by-step routine based on their skin type"
        ]
      }
    },
    {
      "id": "1rc7uxf",
      "title": "help with hair /styling products",
      "content": "First photo was about 6 years ago when i just used whatever my mum bought and let it air dry, and second and third is last few weeks. Not sure what type of hair i have and only in the last year have i started taking proper care of it rather than just straightening it all the time. Used to use noughty curl defining wave shampoo and just whatever conditioner i had then 10 in 1 miracle spray, umberto curl jelly scrunched in and diffused upside down .  Since december i use redken shampoo and conditioner and same spray and jelly/diffuse routine.\n\nIm wondering if its just years of straightening it thats messed with it but is there any good curl cremes that wont break the bank to just define my waves a bit more like the first photo? Ideally available in the uk, ive tried a few different routines on tiktok but none seemed to be any better than what im currently doing. I get so many compliments when i wear it like the second pics but im just wondering if theres anything more i can do lol. Its not nearly as thick as it used to be either so i dont want to overload it with anything heavy. Many thanks in advsnce !",
      "content_preview": "First photo was about 6 years ago when i just used whatever my mum bought and let it air dry, and second and third is last few weeks. Not sure what ty...",
      "content_length": 1118,
      "subreddit": "curlyhair",
      "subreddit_color": "#ff6b35",
      "subreddit_display": "r/curlyhair",
      "url": "https://reddit.com/r/curlyhair/comments/1rc7uxf/help_with_hair_styling_products/",
      "score": 2,
      "comments": 2,
      "engagement_score": 4,
      "created_utc": 1771821226.0,
      "age_human": "13m ago",
      "age_seconds": 826.0338160991669,
      "author": "emperorsnewgr00ve",
      "has_images": true,
      "image_urls": [
        {
          "url": "https://preview.redd.it/hives6n6a6lg1.jpg?width=814&format=pjpg&auto=webp&s=2e15f1aa5251c0328996adc053e9bceb3ec0eb68",
          "width": 814,
          "height": 1213,
          "type": "gallery"
        },
        {
          "url": "https://preview.redd.it/z39xk7n6a6lg1.jpg?width=1206&format=pjpg&auto=webp&s=8e9e7b135cdabd7eba0e979ae83306ba042c8590",
          "width": 1206,
          "height": 2399,
          "type": "gallery"
        },
        {
          "url": "https://preview.redd.it/tdpgq7n6a6lg1.jpg?width=1206&format=pjpg&auto=webp&s=57b029b8a00225e23e6cf1b30831106c4def2d5a",
          "width": 1206,
          "height": 1545,
          "type": "gallery"
        }
      ],
      "image_count": 3,
      "flair": "Help!",
      "is_self": false,
      "permalink": "/r/curlyhair/comments/1rc7uxf/help_with_hair_styling_products/",
      "relevance_score": 100,
      "combined_score": 8.121604690771411,
      "engagement_score_original": 4,
      "opportunity_rating": "low",
      "context": {
        "triggered_keywords": [
          "shampoo",
          "routine",
          "conditioner",
          "products"
        ],
        "help_type": "hair_concern",
        "help_type_confidence": 0.4,
        "expertise_match": [
          "skincare routine",
          "product recommendations",
          "vitamin c serum",
          "pH balance",
          "hair loss treatment",
          "curly hair care",
          "hair growth",
          "hair oils",
          "skincare",
          "haircare",
          "product",
          "problem-solving"
        ],
        "response_angles": [
          "Share your hair care experience",
          "Suggest products for their hair type",
          "Recommend professional consultation if needed"
        ],
        "urgency_level": "low",
        "competition_analysis": {
          "comment_count": 2,
          "engagement_level": "low",
          "response_opportunity": "good"
        },
        "confidence_score": 1.0,
        "response_suggestions": [
          "General match - provide helpful information and ask questions to understand their needs better",
          "Your expertise in skincare routine, product recommendations is highly relevant",
          "Consider these approaches: Share your hair care experience, Suggest products for their hair type"
        ]
      }
    },
    {
      "id": "1rc067w",
      "title": "Best products for volume/frizz control for someone with sensory problems?",
      "content": "Hi, so I have fairly curly, short hair, and recently it just kinda gets.... poofy, like expands sideways and is frizzy. I have virtually no hair routine, aside from shampooing(Pantene daily moisture renewal 72 hr conditioner) and conditioning(Pantene daily moisture renewal 72 hr conditioner) every other day, but I'd like to start one. I almost never comb my hair, but I've tried to, and it never really sticks. I also bike everywhere, so I'd like to last a bit because I have to wear a helmet. I have sensory problems with my hair and hands, so I can't stand anything powdery, oily, greasy, or like a silicon type product because it stresses me out. I also want something that doesn't really have any smell because I nauseous really easily with scented hair product. Does anyone have any good recommendations?",
      "content_preview": "Hi, so I have fairly curly, short hair, and recently it just kinda gets.... poofy, like expands sideways and is frizzy. I have virtually no hair routi...",
      "content_length": 811,
      "subreddit": "curlyhair",
      "subreddit_color": "#ff6b35",
      "subreddit_display": "r/curlyhair",
      "url": "https://reddit.com/r/curlyhair/comments/1rc067w/best_products_for_volumefrizz_control_for_someone/",
      "score": 1,
      "comments": 5,
      "engagement_score": 6,
      "created_utc": 1771800323.0,
      "age_human": "6h ago",
      "age_seconds": 21729.0343170166,
      "author": "Psydameous_Sharm",
      "has_images": true,
      "image_urls": [
        {
          "url": "https://preview.redd.it/yliaer01k4lg1.jpeg?auto=webp&s=7abade92a9eddd7102fc6f7b6408d8bc03e6bb72",
          "width": 1576,
          "height": 2100,
          "type": "preview"
        }
      ],
      "image_count": 1,
      "flair": "Help!",
      "is_self": false,
      "permalink": "/r/curlyhair/comments/1rc067w/best_products_for_volumefrizz_control_for_someone/",
      "relevance_score": 100,
      "combined_score": 8.083872502118348,
      "engagement_score_original": 6,
      "opportunity_rating": "low",
      "context": {
        "triggered_keywords": [
          "shampoo",
          "routine",
          "conditioner",
          "products"
        ],
        "help_type": "product_recommendation",
        "help_type_confidence": 0.5,
        "expertise_match": [
          "skincare routine",
          "product recommendations",
          "vitamin c serum",
          "hair loss treatment",
          "curly hair care",
          "hair growth",
          "hair oils",
          "skincare",
          "haircare",
          "product",
          "problem-solving"
        ],
        "response_angles": [
          "Recommend specific products you've used",
          "Suggest budget-friendly alternatives",
          "Share your experience with similar products"
        ],
        "urgency_level": "low",
        "competition_analysis": {
          "comment_count": 5,
          "engagement_level": "medium",
          "response_opportunity": "moderate"
        },
        "confidence_score": 1.0,
        "response_suggestions": [
          "Moderate match for product_recommendation - share relevant experience and ask clarifying questions",
          "Your expertise in skincare routine, product recommendations is highly relevant",
          "Consider these approaches: Recommend specific products you've used, Suggest budget-friendly alternatives"
        ]
      }
    }
  ],
  "subreddits": [
    "SkincareAddiction",
    "Hair",
    "curlyhair",
    "beauty",
    "IndianSkincareAddicts",
    "HaircareScience"
  ]
}